<code object <module> at #0, file "testcorpus/95_annotation_global.py", line 1>
  1           0 LOAD_CONST               0 ('<code object f at #1, file "testcorpus/95_annotation_global.py", line 1>')
              2 LOAD_CONST               1 ('f')
              4 MAKE_FUNCTION            0
              6 STORE_NAME               0 (f)
              8 LOAD_CONST               2 (None)
             10 RETURN_VALUE
co_argcount: 0
co_kwonlyargcount: 0
co_consts: ('<code object f at #1, file "testcorpus/95_annotation_global.py", line 1>', 'f', None)
co_firstlineno: 1
co_names: ('f',)
co_varnames: ()
co_cellvars: ()
co_freevars: ()
co_lnotab: b''

<code object f at #1, file "testcorpus/95_annotation_global.py", line 1>
  3           0 LOAD_GLOBAL              0 (print)
              2 LOAD_GLOBAL              1 (some_global)
              4 CALL_FUNCTION            1
              6 POP_TOP
              8 LOAD_CONST               0 (None)
             10 RETURN_VALUE
co_argcount: 0
co_kwonlyargcount: 0
co_consts: (None,)
co_firstlineno: 1
co_names: ('print', 'some_global')
co_varnames: ()
co_cellvars: ()
co_freevars: ()
co_lnotab: b'\x00\x02'

